Metadata-Version: 1.0
Name: dtoolai
Version: 0.1.0
Summary: dtool AI utils
Home-page: http://github.com/JIC-CSB/dtoolai
Author: Matthew Hartley
Author-email: Matthew.Hartley@jic.ac.uk
License: MIT
Platform: UNKNOWN
